python_dycasbin/__init__.py
python_dycasbin/adapter.py
python_dycasbin/test_adapter.py
python_dycasbin-0.4.1.dist-info/LICENSE
python_dycasbin-0.4.1.dist-info/METADATA
python_dycasbin-0.4.1.dist-info/WHEEL
python_dycasbin-0.4.1.dist-info/top_level.txt
python_dycasbin-0.4.1.dist-info/RECORD
