Metadata-Version: 2.1
Name: python-dycasbin
Version: 0.4.1
Summary: DynamoDB adopter for casbin
Home-page: https://github.com/abqadeer/python-dynacasbin
Author: Abdul Qadeer
Author-email: abqdr.is@gmail.com
License: UNKNOWN
Keywords: casbindynamodb,aws,boto3,casbin-adapter,rbac,access control,abac,acl,permission
Platform: UNKNOWN
Classifier: Programming Language :: Python :: 3
Classifier: License :: OSI Approved :: MIT License
Classifier: Operating System :: OS Independent
License-File: LICENSE
Requires-Dist: casbin (>=0.8.4)
Requires-Dist: boto3 (>=1.4.0)
